{
    "name": "Global Information",
    "numberOfRequests": {
        "total": 780,
        "ok": 780,
        "ko": 0
    },
    "minResponseTime": {
        "total": 8,
        "ok": 8,
        "ko": -1
    },
    "maxResponseTime": {
        "total": 12633,
        "ok": 12633,
        "ko": -1
    },
    "meanResponseTime": {
        "total": 1069,
        "ok": 1069,
        "ko": -1
    },
    "standardDeviation": {
        "total": 2641,
        "ok": 2641,
        "ko": -1
    },
    "percentiles1": {
        "total": 8743,
        "ok": 8743,
        "ko": -1
    },
    "percentiles2": {
        "total": 11904,
        "ok": 11904,
        "ko": -1
    },
    "group1": {
        "name": "t < 800 ms",
        "count": 662,
        "percentage": 85
    },
    "group2": {
        "name": "800 ms < t < 1200 ms",
        "count": 4,
        "percentage": 1
    },
    "group3": {
        "name": "t > 1200 ms",
        "count": 114,
        "percentage": 15
    },
    "group4": {
        "name": "failed",
        "count": 0,
        "percentage": 0
    },
    "meanNumberOfRequestsPerSecond": {
        "total": 0.10968045303089276,
        "ok": 0.10968045303089276,
        "ko": -1.0
    }
}